MANIFEST.in
README.md
setup.cfg
setup.py
mypycalculatelib/__init__.py
mypycalculatelib/app.py
mypycalculatelib/mycalculator.py
mypycalculatelib.egg-info/PKG-INFO
mypycalculatelib.egg-info/SOURCES.txt
mypycalculatelib.egg-info/dependency_links.txt
mypycalculatelib.egg-info/entry_points.txt
mypycalculatelib.egg-info/requires.txt
mypycalculatelib.egg-info/top_level.txt
mypycalculatelib/static/index.html
mypycalculatelib/static/css/main.css
mypycalculatelib/static/css/style.css
mypycalculatelib/templates/index.html
mypycalculatelib/templates/results.html